Bgm/__init__.py
Bgm/bgm1.mp3
Bgm/bgm2.mp3
Bgm/bgm3.mp3
Bgm/bgm4.mp3
Bgm/bgm5.mp3
Bgm/bgm6.mp3
Bgm/bgm7.mp3
Bgm/bgm8.mp3
Images/1.png
Images/10.png
Images/2.png
Images/3.png
Images/4.png
Images/5.png
Images/6.png
Images/7.png
Images/8.png
Images/9.png
Images/__init__.py
mc_klotski-0.0.6.data/data/mc_klotski.py
mc_klotski-0.0.6.data/data/Bgm/bgm1.mp3
mc_klotski-0.0.6.data/data/Bgm/bgm2.mp3
mc_klotski-0.0.6.data/data/Bgm/bgm3.mp3
mc_klotski-0.0.6.data/data/Bgm/bgm4.mp3
mc_klotski-0.0.6.data/data/Bgm/bgm5.mp3
mc_klotski-0.0.6.data/data/Bgm/bgm6.mp3
mc_klotski-0.0.6.data/data/Bgm/bgm7.mp3
mc_klotski-0.0.6.data/data/Bgm/bgm8.mp3
mc_klotski-0.0.6.data/data/Images/1.png
mc_klotski-0.0.6.data/data/Images/10.png
mc_klotski-0.0.6.data/data/Images/2.png
mc_klotski-0.0.6.data/data/Images/3.png
mc_klotski-0.0.6.data/data/Images/4.png
mc_klotski-0.0.6.data/data/Images/5.png
mc_klotski-0.0.6.data/data/Images/6.png
mc_klotski-0.0.6.data/data/Images/7.png
mc_klotski-0.0.6.data/data/Images/8.png
mc_klotski-0.0.6.data/data/Images/9.png
mc_klotski-0.0.6.data/data/ogg/1.ogg
mc_klotski-0.0.6.data/data/ogg/2.ogg
mc_klotski-0.0.6.data/data/ogg/3.ogg
mc_klotski-0.0.6.data/data/ogg/4.ogg
mc_klotski-0.0.6.data/data/ogg/5.ogg
mc_klotski-0.0.6.data/data/ogg/6.ogg
ogg/1.ogg
ogg/2.ogg
ogg/3.ogg
ogg/4.ogg
ogg/5.ogg
ogg/6.ogg
ogg/__init__.py
mc_klotski-0.0.6.dist-info/METADATA
mc_klotski-0.0.6.dist-info/WHEEL
mc_klotski-0.0.6.dist-info/top_level.txt
mc_klotski-0.0.6.dist-info/RECORD
